setup.py
binpack/__init__.py
bp.egg-info/PKG-INFO
bp.egg-info/SOURCES.txt
bp.egg-info/dependency_links.txt
bp.egg-info/top_level.txt