Metadata-Version: 1.0
Name: bp
Version: 0.0.3
Summary: Binpack implementation for python
Home-page: https://github.com/binpack/binpack-python
Author: http://www.liaohuqiu.net
Author-email: liaohuqiu@gmail.com
License: MIT License
Keywords: binpack
Platform: any
